gramo/__init__.py
gramo/main.py
gramo-0.1.1.dist-info/LICENSE
gramo-0.1.1.dist-info/METADATA
gramo-0.1.1.dist-info/WHEEL
gramo-0.1.1.dist-info/top_level.txt
gramo-0.1.1.dist-info/RECORD
