Metadata-Version: 2.2
Name: gramo
Version: 0.1.1
License-File: LICENSE
Dynamic: description
Dynamic: description-content-type
